structlab/__init__.py
structlab/main.py
structlab/cli/commands.py
structlab/core/__init__.py
structlab/core/build_struct.py
structlab/core/scan_struct.py
structlab/utils/__init__.py
structlab/utils/cli_helper.py
structlab/utils/detect_env.py
structlab/utils/exclude.py
structlab/utils/printer.py
structlab-0.1.0.dist-info/licenses/LICENSE
structlab-0.1.0.dist-info/METADATA
structlab-0.1.0.dist-info/WHEEL
structlab-0.1.0.dist-info/entry_points.txt
structlab-0.1.0.dist-info/top_level.txt
structlab-0.1.0.dist-info/RECORD
