Metadata-Version: 2.4
Name: structlab
Version: 0.1.0
Summary: Structlab is a lightweight Python CLI tool that helps you scaffold both folders and files from customizable structures. Define reusable templates, choose your terminal type, and generate complete project layouts in seconds — ideal for rapid project bootstrapping.
Author-email: Anex Lab <anexlab.dev@gmail.com>
License: MIT
Requires-Python: >=3.7
License-File: LICENSE
Requires-Dist: argparse
Dynamic: license-file
